gitbranchhealth
