Metadata-Version: 1.0
Name: gitbranchhealth
Version: 0.2.2
Summary: ('A tool for determining the health of branches in a git repository',)
Home-page: http://github.com/jwir3/gitbranchhealth
Author: Scott Johnson
Author-email: jaywir3@gmail.com
License: UNKNOWN
Platform: UNKNOWN
